{
  "ablation_dir": "D:\\python\\dissertation\\Model Runs\\ablations\\sticky_execution\\run_20260415_010019",
  "block_lengths": [
    3,
    5,
    10,
    15,
    20
  ],
  "n_bootstrap": 1000,
  "strategy_summary_file": "D:\\python\\dissertation\\Model Runs\\robustness\\bootstrap_block_sensitivity\\run_20260415_011524\\block_length_strategy_summary.csv",
  "difference_summary_file": "D:\\python\\dissertation\\Model Runs\\robustness\\bootstrap_block_sensitivity\\run_20260415_011524\\block_length_difference_summary.csv"
}